albus/__init__.py
albus/application/agents/__init__.py
albus/application/agents/service.py
albus/application/agents/skills/__init__.py
albus/application/agents/skills/code/SKILL.md
albus/application/agents/skills/code/pathway.py
albus/application/agents/skills/files/SKILL.md
albus/application/agents/skills/files/pathway.py
albus/application/agents/skills/research/SKILL.md
albus/application/agents/skills/research/pathway.py
albus/application/pathways/__init__.py
albus/application/pathways/service.py
albus/application/ports/__init__.py
albus/application/ports/runtime_port.py
albus/application/ports/thread_repository.py
albus/application/runtime.py
albus/application/state_machine/__init__.py
albus/application/state_machine/builtin.py
albus/application/state_machine/controller.py
albus/application/state_machine/host_pathways.py
albus/application/state_machine/intent_router.py
albus/domain/runs/state_machine.py
albus/domain/world/thread.py
albus/infrastructure/config.py
albus/infrastructure/deployment.py
albus/infrastructure/errors.py
albus/infrastructure/middleware.py
albus/infrastructure/observability/__init__.py
albus/infrastructure/observability/debug.py
albus/infrastructure/observability/emitter.py
albus/infrastructure/observability/events.py
albus/infrastructure/observability/logging_config.py
albus/infrastructure/observability/pathway_vm_bridge.py
albus/infrastructure/observability/run_recorder.py
albus/infrastructure/observability/spans.py
albus/infrastructure/repositories/__init__.py
albus/infrastructure/repositories/state_machine_repository.py
albus/infrastructure/repositories/thread_repository.py
albus/sdk.py
albus/transport/__init__.py
albus/transport/cli.py
albus/transport/handlers/__init__.py
albus/transport/handlers/agents.py
albus/transport/handlers/chat.py
albus/transport/handlers/docs.py
albus/transport/handlers/infrastructure.py
albus/transport/handlers/pathways.py
albus/transport/handlers/runs.py
albus/transport/handlers/threads.py
albusos-0.6.1.dist-info/WHEEL
albusos-0.6.1.dist-info/entry_points.txt
albusos-0.6.1.dist-info/METADATA
albusos-0.6.1.dist-info/RECORD
