Metadata-Version: 2.4
Name: albusos
Version: 0.6.1
Summary: Albus AgentOS - Event-driven AI agent runtime
Author: Your Name
Author-email: Your Name <your.email@example.com>
License-Expression: MIT
Classifier: Programming Language :: Python :: 3
Classifier: Programming Language :: Python :: 3.11
Classifier: Programming Language :: Python :: 3.12
Classifier: Programming Language :: Python :: 3.13
Classifier: Programming Language :: Python :: 3.14
Requires-Dist: pydantic>=2.0,<3
Requires-Dist: aiohttp>=3.9,<4
Requires-Dist: ddgs>=9.0,<10
Requires-Dist: idna>=3.6,<4
Requires-Dist: openai>=1.0,<2
Requires-Dist: anthropic>=0.20,<0.21
Requires-Dist: python-dotenv>=1.0,<2
Requires-Dist: aiostream>=0.6.4,<0.7
Requires-Dist: pyyaml>=6.0.3,<7
Requires-Dist: mcp>=1.0,<2
Requires-Dist: google-generativeai>=0.5,<0.6 ; extra == 'all'
Requires-Dist: google-generativeai>=0.5,<0.6 ; extra == 'google'
Requires-Python: >=3.11, <4
Provides-Extra: all
Provides-Extra: google
